README.md
setup.cfg
setup.py
qoaladep/__init__.py
qoaladep.egg-info/PKG-INFO
qoaladep.egg-info/SOURCES.txt
qoaladep.egg-info/dependency_links.txt
qoaladep.egg-info/top_level.txt
qoaladep/aws/__init__.py
qoaladep/aws/face/__init__.py
qoaladep/aws/face/verify.py
qoaladep/aws/textract/__init__.py
qoaladep/aws/textract/textract.py
qoaladep/aws/textract/utils.py
qoaladep/gcp/__init__.py
qoaladep/gcp/bigquery/__init__.py
qoaladep/gcp/bigquery/bigquery.py
qoaladep/gcp/datastore/__init__.py
qoaladep/gcp/datastore/datastore.py
qoaladep/gcp/ml_engine/__init__.py
qoaladep/gcp/ml_engine/deploy_model.py
qoaladep/gcp/ml_engine/predict_model.py
qoaladep/gcp/ml_engine/train_model.py
qoaladep/gcp/ocr/__init__.py
qoaladep/gcp/ocr/ocr.py
qoaladep/gcp/pubsub/__init__.py
qoaladep/gcp/pubsub/pubsub.py
qoaladep/gcp/storage/__init__.py
qoaladep/gcp/storage/storage.py
qoaladep/utils/__init__.py
qoaladep/utils/detector_utils.py
qoaladep/utils/image_utils.py