Metadata-Version: 2.1
Name: qoaladep
Version: 0.2.2
Summary: qoala.id data science team library for deployment model
Home-page: UNKNOWN
Author: qoala deployment team
License: UNKNOWN
Platform: UNKNOWN
